README.rst
setup.py
cli/__init__.py
cli/script.py
codegrapher/__init__.py
codegrapher/graph.py
codegrapher/parser.py
codegrapher.egg-info/PKG-INFO
codegrapher.egg-info/SOURCES.txt
codegrapher.egg-info/dependency_links.txt
codegrapher.egg-info/entry_points.txt
codegrapher.egg-info/pbr.json
codegrapher.egg-info/requires.txt
codegrapher.egg-info/top_level.txt
tests/__init__.py
tests/test_graph.py
tests/test_parser.py