Metadata-Version: 1.1
Name: codegrapher
Version: 0.2.1
Summary: Code that graphs code
Home-page: http://github.com/LaurEars/codegrapher
Author: Laura Rupprecht
Author-email: lauracr@bu.edu
License: UNKNOWN
Platform: UNKNOWN
Classifier: Development Status :: 4 - Beta
Classifier: Intended Audience :: Developers
Classifier: License :: OSI Approved :: MIT License
Classifier: Programming Language :: Python :: 2.7
Classifier: Programming Language :: Python :: 2 :: Only
Classifier: Topic :: Software Development :: Documentation
